cli/__init__.py
cli/morse.py
morsecodetranslator/__init__.py
morsecodetranslator/morse.py
morse_transcript-0.0.3.dist-info/LICENSE.md
morse_transcript-0.0.3.dist-info/METADATA
morse_transcript-0.0.3.dist-info/WHEEL
morse_transcript-0.0.3.dist-info/entry_points.txt
morse_transcript-0.0.3.dist-info/top_level.txt
morse_transcript-0.0.3.dist-info/RECORD
