Metadata-Version: 2.1
Name: morse-transcript
Version: 0.0.3
Summary: Convert text to Morse Code and vise-versa.
Home-page: https://github.com/gugupy/morsecodetranslator
Author: Gughanathan M
Author-email: gugu.ap900@gmail.com
License: MIT
Keywords: MorseCode,Morse
Classifier: Programming Language :: Python :: 3
Classifier: Operating System :: OS Independent
Requires-Python: >=3.6
License-File: LICENSE.md
